CongSuanfaShejiDaoYingxianLuojiDeShixianFuzaShuziLuojixitongDeVerilogHdlShejiJishuHeFangfa/README.md
CongSuanfaShejiDaoYingxianLuojiDeShixianFuzaShuziLuojixitongDeVerilogHdlShejiJishuHeFangfa/__init__.py
CongSuanfaShejiDaoYingxianLuojiDeShixianFuzaShuziLuojixitongDeVerilogHdlShejiJishuHeFangfa/__main__.py
CongSuanfaShejiDaoYingxianLuojiDeShixianFuzaShuziLuojixitongDeVerilogHdlShejiJishuHeFangfa/file.pdf
CongSuanfaShejiDaoYingxianLuojiDeShixianFuzaShuziLuojixitongDeVerilogHdlShejiJishuHeFangfa/index.html
cong_suanfa_sheji_dao_yingxian_luoji_de_shixian_fuza_shuzi_luojixitong_de_verilog_hdl_sheji_jishu_he_fangfa-2024.3.3.0.dist-info/METADATA
cong_suanfa_sheji_dao_yingxian_luoji_de_shixian_fuza_shuzi_luojixitong_de_verilog_hdl_sheji_jishu_he_fangfa-2024.3.3.0.dist-info/WHEEL
cong_suanfa_sheji_dao_yingxian_luoji_de_shixian_fuza_shuzi_luojixitong_de_verilog_hdl_sheji_jishu_he_fangfa-2024.3.3.0.dist-info/entry_points.txt
cong_suanfa_sheji_dao_yingxian_luoji_de_shixian_fuza_shuzi_luojixitong_de_verilog_hdl_sheji_jishu_he_fangfa-2024.3.3.0.dist-info/top_level.txt
cong_suanfa_sheji_dao_yingxian_luoji_de_shixian_fuza_shuzi_luojixitong_de_verilog_hdl_sheji_jishu_he_fangfa-2024.3.3.0.dist-info/RECORD
