Metadata-Version: 2.1
Name: cong-suanfa-sheji-dao-yingxian-luoji-de-shixian-fuza-shuzi-luojixitong-de-verilog-hdl-sheji-jishu-he-fangfa
Version: 2024.3.3.0
Summary: 从算法设计到硬线逻辑的实现--复杂数字逻辑系统的 Verilog HDL 设计技术和方法
Home-page: https://github.com/apachecn/cong-suanfa-sheji-dao-yingxian-luoji-de-shixian-fuza-shuzi-luojixitong-de-verilog-hdl-sheji-jishu-he-fangfa
Author: ApacheCN
Author-email: apachecn@163.com
License: UNKNOWN
Platform: UNKNOWN
Classifier: Development Status :: 4 - Beta
Classifier: Environment :: Console
Classifier: Intended Audience :: Developers
Classifier: Intended Audience :: End Users/Desktop
Classifier: License :: Other/Proprietary License
Classifier: Natural Language :: Chinese (Simplified)
Classifier: Natural Language :: English
Classifier: Operating System :: OS Independent
Classifier: Programming Language :: Python :: 3
Classifier: Programming Language :: Python :: 3 :: Only
Classifier: Programming Language :: Python :: 3.6
Classifier: Programming Language :: Python :: 3.7
Classifier: Topic :: Text Processing :: Markup :: Markdown
Classifier: Topic :: Text Processing :: Markup :: HTML
Classifier: Topic :: Internet :: WWW/HTTP
Classifier: Topic :: Software Development :: Documentation
Classifier: Topic :: Documentation
Requires-Python: >=3.6
